goodwan_client/__init__.py
goodwan_client/classes.py
goodwan_client/client.py
goodwan_client/devices.py
goodwan_client/errors.py
goodwan_client/event.py
goodwan_client/helpers.py
goodwan_client/serializer.py
goodwan_client-0.2.dist-info/LICENSE.md
goodwan_client-0.2.dist-info/METADATA
goodwan_client-0.2.dist-info/WHEEL
goodwan_client-0.2.dist-info/top_level.txt
goodwan_client-0.2.dist-info/RECORD
