Metadata-Version: 2.1
Name: goodwan-client
Version: 0.2
Summary: GoodWan IoT client module
Home-page: https://github.com/kanavis/goodwan_client
Author: Kanavis
Author-email: dkanavis@gmail.com
License: MIT
Keywords: goodwan,iot
Platform: UNKNOWN
Classifier: License :: OSI Approved :: MIT License
Classifier: Programming Language :: Python :: 3
Classifier: Programming Language :: Python :: 3.5
Classifier: Programming Language :: Python :: 3.6
Classifier: Programming Language :: Python :: 3.7
Requires-Dist: requests
Requires-Dist: pytz
